django_mailomat/__init__.py
django_mailomat/backend.py
django_mailomat-0.5.0.dist-info/METADATA
django_mailomat-0.5.0.dist-info/WHEEL
django_mailomat-0.5.0.dist-info/licenses/LICENSE
django_mailomat-0.5.0.dist-info/RECORD
