Metadata-Version: 2.4
Name: django-mailomat
Version: 0.5.0
Summary: Django email backend for Mailomat API
Project-URL: Homepage, https://github.com/liip-amboss/django-mailomat
Project-URL: Repository, https://github.com/liip-amboss/django-mailomat.git
Author-email: Liip AG <info@liip.ch>
License-Expression: MIT
License-File: LICENSE
Keywords: django,email,mailomat
Classifier: Development Status :: 4 - Beta
Classifier: Framework :: Django
Classifier: Framework :: Django :: 3.2
Classifier: Framework :: Django :: 4.0
Classifier: Framework :: Django :: 4.1
Classifier: Framework :: Django :: 4.2
Classifier: Framework :: Django :: 5.0
Classifier: Framework :: Django :: 5.1
Classifier: Framework :: Django :: 5.2
Classifier: Intended Audience :: Developers
Classifier: License :: OSI Approved :: MIT License
Classifier: Programming Language :: Python :: 3
Classifier: Programming Language :: Python :: 3.9
Classifier: Programming Language :: Python :: 3.10
Classifier: Programming Language :: Python :: 3.11
Classifier: Programming Language :: Python :: 3.12
Classifier: Programming Language :: Python :: 3.13
Requires-Python: >=3.9
Requires-Dist: django>=3.2
Requires-Dist: requests>=2.31.0
